naiximing/__init__.py
naiximing/core/__init__.py
naiximing/core/cv_tool/__init__.py
naiximing/core/cv_tool/cut_image/__init__.py
naiximing/core/cv_tool/cut_image/cut_convert.py
naiximing/core/cv_tool/pdf_ocr/__init__.py
naiximing/core/cv_tool/pdf_ocr/script/__init__.py
naiximing/core/cv_tool/pdf_ocr/script/pdf_ocr.py
naiximing/core/cv_tool/word_cloud/__init__.py
naiximing/core/cv_tool/word_cloud/word_cloud.py
naiximing/core/ml_tool/__init__.py
naiximing/core/nlp_tool/__init__.py
naiximing/utils/__init__.py
naiximing-0.0.2.dist-info/LICENSE
naiximing-0.0.2.dist-info/METADATA
naiximing-0.0.2.dist-info/WHEEL
naiximing-0.0.2.dist-info/top_level.txt
naiximing-0.0.2.dist-info/RECORD
