Metadata-Version: 2.1
Name: naiximing
Version: 0.0.2
Summary: 各种有趣的工具合集.
Home-page: https://github.com/AxsPlayer/Tool_AI-Task
Author: kexi
Author-email: 498100059@qq.com
License: UNKNOWN
Platform: UNKNOWN
Classifier: Programming Language :: Python :: 3
Classifier: License :: OSI Approved :: MIT License
Classifier: Operating System :: OS Independent
License-File: LICENSE
Requires-Dist: Pillow
